ai_datasense/__init__.py
ai_datasense/core.py
ai_datasense/utils.py
ai_datasense-0.1.0.dist-info/LICENSE
ai_datasense-0.1.0.dist-info/METADATA
ai_datasense-0.1.0.dist-info/WHEEL
ai_datasense-0.1.0.dist-info/top_level.txt
ai_datasense-0.1.0.dist-info/RECORD
