Metadata-Version: 2.1
Name: ai_datasense
Version: 0.1.0
Summary: AI-powered data insights and anomaly detection
Author-email: Ahmed Bin Khalid <ahmed.khalid2108@gmail.com>
License: MIT
Project-URL: Repository, https://github.com/abkmy/ai_datasense
Project-URL: Documentation, https://github.com/abkmy/ai_datasense/wiki
Requires-Python: >=3.7
License-File: LICENSE
Requires-Dist: pandas>=1.0
Requires-Dist: matplotlib>=3.0
Requires-Dist: openai>=1.0
